finance_calendars/__init__.py
finance_calendars/finance_calendars.py
finance_calendars-0.0.7.dist-info/METADATA
finance_calendars-0.0.7.dist-info/WHEEL
finance_calendars-0.0.7.dist-info/top_level.txt
finance_calendars-0.0.7.dist-info/RECORD
