Metadata-Version: 2.1
Name: finance_calendars
Version: 0.0.7
Summary: Simple wrapper of the NASDAQ Public API, provides data on earnings calendar, IPO calendar, dividends calendar etc.
Home-page: https://github.com/s-kerin/finance_calendars
Author: Stephen Kerin
Author-email: skerin@gmail.com
License: UNKNOWN
Project-URL: Bug Tracker, https://github.com/s-kerin/finance_calendars/issues
Platform: UNKNOWN
Classifier: Programming Language :: Python :: 3
Classifier: License :: OSI Approved :: MIT License
Classifier: Operating System :: OS Independent
Requires-Python: >=3.6
